{"paths":{},"types":[],"uuids":["e3j0MCXaVALbl8Vpvcdnmo","1fwz3wIetDho4s8IhWij1X","29FYIk+N1GYaeWH/q1NxQO","56Od/OSLRMQ78z1OMjr/+X","943fbWrqNLq56lDzl2d+bw","c2qsawZy1EaIHkhsDByeZf","c3Mrci0qJKC6tQ63m76gg6","269v+hCGlPYKMIco6y33js","8fD7Kmdq9DZbouGQN46ISt","91+wY8+ItAp7rQ/N98ZstT","c7imWKBjZKPKvDdRX9hHKq","07RQQs1kVMrZLPu8UYf3HW","0dGl9Fw75B4Iiy8RatISvN","0fzdHzPnBDvL3EsgzCVZEn","10r8Sen6xKFLGs9PBtuRZ/","13ZEZ6RJxGnrKJtm9JaxmS","135zXi93xNNYiO6wVlHTv0","14VGlL++5LgZujioG6KqQh","1ciLBOHvNPJ5jWmEaRAhe/","27xJ0I8SlMaKjqLMnDZW6i","2aGvNiJQpL17GnkfDSFaZM","2b8Dv+PhxIAqw2n6ZXWoLw","2cHxqwiDxDHZ+xRh8QPweK","2doaOBxTdJiZA0GM4LNWM8","31u2eqU5lCt7lXQxZiIXaW","32Bj2yK2tOpqg3iFnZ70XJ","38ypAibSlFbraVj2Nc3kdp","3ajwMDXhFHY7SjC7BD3r70","3a9PNECq1GopPQuZtrP08U","43t2MURypKX6+2XqR3+uQ1","47/fNWXJ1DB52UMXpJCpJF","4c9dsAt+VEPKg2wAeaW6f9","4eXdk2/2RGp6pVZTl+IcRI","551/8t3hxL+4iRgw7KZ6tK","555wNmpOdFjYneHSCuYxlM","60f2Vgl5xM75wKTM1SvlhM","61+vW1WctLyoOs13mL6hYB","66UaszqjxOOozBC+1E08ti","71VhFCTINJM6/Ky3oX9nBT","72Pz4/bHtCFKaQrQvOMN4b","778w/iDzRJi7audmIk56vS","7attBIWIlGq7kdH5d9Q7yf","7a6ScafzZO/YV5Eu752NUI","7feI87Vl1P+YWt/G/pvfAc","80dMcMvJRAgqV3pwXT1UHL","84qIIa5llNxZLoTpjvq6/M","85R4LDiZZL4YXrhp1rVXRu","8bupqKkPZDRJOwUv37WbZ5","91fRxv1kZAfbTb9Fl52V8P","93Ww2V90dOpbnjkO+KvwaA","957Qy6GjRMU5sMe7zwKB5A","98lfoxv5xDvoh6GFYz85r6","9ah5GhrvND8aEfOxw78wrH","9bycmoDjlIuZ11jCvJIJ2E","a0khKnxnBC6YNzDxb0+uIo","a1Ob7tHNBBFr3drvpUIowk","abgk1Bq9pHHafnW+nRKkxV","b5M1mi+WdFyqPNzhPqjFT8","beKCb8ELtEkb/pcLF+YsJb","c0cv1eZPRCfqYf7N00WAtn","c3p5ZbYz1PtpSfW1MGX6uP","c6Jk23/nJIU4Q8UP3QFhcn","c9IvK0Tg5AaKU1urEmreA2","ccFOJWnItNHbqzT5dmzjCY","d6qrNk+59BhqUEnEkUgQpq","e7aGtykUlLrIqeY1vQefOe","e9hOhtJxNDm6n9swjGDxFp","eceLXdIHdIjp/oinWOPsi8","edJ5EVMh5OWLrs/GXQ2uCh","f0q5dOWMRAGLAYkUK6f+QM","f6WbZt3L5EZZ5wrB9pbKHr","f7PWF+hYxEX7G5gGuRnIgV","fdXye84pJO57ub+f7dnRvh","fdi5x1EVhGToc2iax1s7Lq","02CvjGbO5N2pyQL1mRKOSJ","0f5ojsuRZKsLJfJGmOe/Vq","10JKYpRyZFZaxrBN/WdJ7H","11k4x7BH5LO7euZVfQW9o1","17IA3DvN1PXb/VU0U7+e01","2d3E1dNltOrpYwqhgd/IW8","2fBHdpHUhPM4iIP8uN9gpD","32Jv8jZG9LN7lfSTtyZtnD","37HHGhTbpN+799IfVK0zXi","39bZf4SPVGLIbdAqDoff8A","3a2h9+s2RIbJQ9nG5Ca6H8","3bRuP4PoFNaI9Zd4YZGYYQ","41kRcfBrtPFaFMrgQnFHEn","4eX/bSpKtGtaQM2OAaubTM","53btZBfpdE3JQWqhMnDfOr","57fp6Hlg1IR5MivzCY2g1m","71+rfcxcJIEbD+T+hU9nnR","7bM/awLtpBoYGRSkybbT3f","7eFsw+V4tM66k251i8NKaR","7elLeRmi9G5bi9fsLCz8n0","82OE920bZGbYBjmxf9a3qb","88zx26HBBDHYbkVRcsHMJl","95TJ6i8xBP/70q/SjMT2Yt","a2AZ+zjG9CvKoEaqzc8tCg","aaAU2Ui/hFWoXDFiIB8Ysp","ac3CFIxWpGbJGpxpYzcl+W","ac7evUy81C9K27EJoPST4z","b0MfbzJhVFsJQ2SoTcQgn9","b6uaUcosVBObJ6gzVs9kO/","bevvOVYttCLZwLIjDfucQc","c9hIb1809MXbeKFjTSFtNv","cbei3iY1FBGabJSOZ3FL4A","ceGFcHe95GnZuAfTvFlJLR","d5bChkmjBJBaO33QW9n6rr","dd+e5tP6tETqUct0Ggh5/l","e3e44ONwpAFaD7LnxO0Kq0","eaonNnAzVINqW4o4YLPDSB","ecpdLyjvZBwrvm+cedCcQy","ef6NBTPwhC2rJsLHLE2OmY","fd9l+gB11OjYEn61Z5md8b"],"scenes":{"db://assets/Scenes/game1.fire":62,"db://assets/Scenes/game2.fire":25,"db://assets/Scenes/game_over.fire":64,"db://assets/Scenes/game_start.fire":28,"db://assets/Scenes/levelSelect.fire":68,"db://assets/Scenes/login.fire":31,"db://assets/Scenes/menu.fire":66,"db://assets/Scenes/signup.fire":52,"db://assets/Scenes/stop.fire":42},"redirect":[111,0],"deps":["internal"],"packs":{"03a35bcc0":[12,1,2,3,4,52,5,6,0],"054f9dfdb":[42,96,98],"062e9a780":[1,2,79,3,36,93,46,4,101,5,6,0,68],"0654fdc9e":[11,16,17,18,21,22,23,24,26,27,29,30,33,35,38,39,40,44,45,48,49,51,53,54,55,59,67,69,70,71,73],"073a50c58":[14,15,7,19,20,37,43,8,9,102,58,60,61,10,62,108,0,72],"078a3bc2a":[81,104],"07cb26d12":[14,15,7,19,20,25,37,43,8,9,99,58,60,61,10,110,112,72],"087b1152c":[106,113],"0a078e926":[74,13,75,76,77,78,7,80,82,83,84,85,86,32,88,34,89,90,41,91,92,94,95,47,8,9,50,97,56,100,57,103,10,105,63,107,109],"0b396dbcc":[12,1,2,31,3,4,5,6,0],"0f20e37b3":[1,2,3,36,46,4,5,6,0,65,66]},"name":"main","importBase":"import","nativeBase":"native","debug":false,"isZip":false,"encrypted":false,"versions":{"import":["03a35bcc0","54930","054f9dfdb","643cc","062e9a780","0d1fd","0654fdc9e","cbbbb","073a50c58","ecde6","078a3bc2a","29ceb","07cb26d12","53c0b","087b1152c","82216","0a078e926","8f828","0b396dbcc","d8fa0","0f20e37b3","c06ba",28,"ba9ff",87,"c4b2a",64,"6961f"],"native":[11,"a9804",13,"35c99",16,"88a6f",17,"e92c4",18,"4a454",21,"921ab",22,"372bd",23,"8054a",24,"fd188",26,"681c7",27,"4d2ef",29,"a2dce",30,"7b4be",32,"050ee",33,"6f7cd",34,"e97c7",35,"9c515",38,"c06a9",39,"45daf",40,"5ab0b",41,"809e0",44,"8eade",45,"52453",47,"8e226",48,"9bc74",49,"2482d",50,"a96f9",51,"a6ba9",53,"71047",54,"0a742",55,"5ab07",56,"f2cea",57,"b9f63",59,"a6ff8",63,"3f32c",65,"7b568",67,"f0d02",69,"5b81d",70,"5fe82",71,"7ac09",73,"3b382"]}}